Metadata-Version: 2.4
Name: music_assistant_models_loose
Version: 0.0.1
Summary: Music Assistant Base Models
Author-email: The Music Assistant Authors <music_assistant@users.noreply.github.com>
License: Apache-2.0
Platform: any
Classifier: Environment :: Console
Classifier: Programming Language :: Python :: 3.10
Classifier: Programming Language :: Python :: 3.11
Classifier: Programming Language :: Python :: 3.12
Classifier: Programming Language :: Python :: 3.13
Requires-Python: >=3.10
License-File: LICENSE
Requires-Dist: orjson>=3.9
Requires-Dist: mashumaro>=3.14
Provides-Extra: test
Requires-Dist: codespell==2.4.1; extra == "test"
Requires-Dist: isort==6.0.1; extra == "test"
Requires-Dist: mypy==1.17.1; extra == "test"
Requires-Dist: pre-commit==4.2.0; extra == "test"
Requires-Dist: pre-commit-hooks==5.0.0; extra == "test"
Requires-Dist: pytest==8.4.1; extra == "test"
Requires-Dist: pytest-cov==6.2.1; extra == "test"
Requires-Dist: tomli==2.2.1; extra == "test"
Requires-Dist: ruff==0.12.7; extra == "test"
Dynamic: license-file
